newsoc_arxiv_bot
